{
  "code": 200,
  "count": 16,
  "data": [
    {
      "appmaxcodeFromTemplate": "",
      "appmincodeFromTemplate": "",
      "countryCode": "OTHER",
      "downUrl": "https://rc.veresource.com/vcm/20200515/17384242/0x06000000000001DF.zip",
      "event": "",
      "eventFromTemplateInfo": "{\"code\":\"0\",\"parameter\":{}}",
      "extend": "{\"orderNoNewUser\":206}",
      "flagForGroup": 0,
      "groupCode": "201911291433262561",
      "height": 1280,
      "hotFlag": 0,
      "iconFromTemplate": "https://d2hyio9ps90xn9.cloudfront.net/videodata/fx/explosion/1.webp",
      "id": 642159,
      "intro": "Explosion",
      "introFromTemplate": "",
      "lang": "en_OTHER",
      "model": "videoshow_effect",
      "newFlag": 0,
      "orderNoFromInfo": 0,
      "orderNoFromTemplate": 0,
      "previewtype": 2,
      "previewurl": "",
      "productId": 2,
      "recommendFlag": 0,
      "showEditFlag": 1,
      "showEditFlagGroup": 1,
      "showImg": "",
      "subTcid": "0",
      "tcid": "6",
      "templateCode": "0x06000000000001DF",
      "templateExtend": "{\"dataType\":\"0\",\"singleVideoDuration\":1000,\"textBindFont\":{}}",
      "templateRule": "{\"type\":\"normal\",\"rule\":{\"changeConfs\":[]},\"remark\":\"\",\"width\":720,\"height\":1280,\"pretreatment_type\":\"\"}",
      "title": "Explosion",
      "titleFromTemplate": "EX-1",
      "version": 196620,
      "virFlag": 0,
      "width": 720
    },
    {
      "appmaxcodeFromTemplate": "",
      "appmincodeFromTemplate": "",
      "countryCode": "OTHER",
      "downUrl": "https://rc.veresource.com/vcm/20191022/14020000/0x0600000000000094.zip",
      "event": "",
      "eventFromTemplateInfo": "{\"code\":\"0\",\"parameter\":{}}",
      "extend": "{\"orderNoNewUser\":206}",
      "flagForGroup": 0,
      "groupCode": "201911291433262561",
      "height": 0,
      "hotFlag": 0,
      "iconFromTemplate": "https://d2hyio9ps90xn9.cloudfront.net/videodata/fx/explosion/2.webp",
      "id": 420477,
      "intro": "Explosion",
      "introFromTemplate": "",
      "lang": "en_OTHER",
      "model": "videoshow_effect",
      "newFlag": 0,
      "orderNoFromInfo": 1,
      "orderNoFromTemplate": 1,
      "previewtype": 3,
      "previewurl": "https://rs.videoshow.mobi/v2/images/vmake/fx/explosion/2.gif",
      "productId": 2,
      "recommendFlag": 0,
      "showEditFlag": 1,
      "showEditFlagGroup": 1,
      "showImg": "",
      "subTcid": "0",
      "tcid": "6",
      "templateCode": "0x0600000000000094",
      "templateExtend": "{\"materialMin\":\"\",\"materialMax\":\"\",\"textBindFont\":{}}",
      "title": "Explosion",
      "titleFromTemplate": "EX-2",
      "version": 131082,
      "virFlag": 0,
      "width": 0
    },
    {
      "appmaxcodeFromTemplate": "",
      "appmincodeFromTemplate": "",
      "countryCode": "OTHER",
      "downUrl": "https://rc.veresource.com/vcm/20191022/12180505/0x06000000000000D4.zip",
      "event": "",
      "eventFromTemplateInfo": "{\"code\":\"0\",\"parameter\":{}}",
      "extend": "{\"orderNoNewUser\":206}",
      "flagForGroup": 0,
      "groupCode": "201911291433262561",
      "height": 0,
      "hotFlag": 0,
      "iconFromTemplate": "https://d2hyio9ps90xn9.cloudfront.net/videodata/fx/explosion/3.webp",
      "id": 420483,
      "intro": "Explosion",
      "introFromTemplate": "",
      "lang": "en_OTHER",
      "model": "videoshow_effect",
      "newFlag": 0,
      "orderNoFromInfo": 2,
      "orderNoFromTemplate": 2,
      "previewtype": 3,
      "previewurl": "https://rs.videoshow.mobi/v2/images/vmake/fx/explosion/3.gif",
      "productId": 2,
      "recommendFlag": 0,
      "showEditFlag": 1,
      "showEditFlagGroup": 1,
      "showImg": "",
      "subTcid": "0",
      "tcid": "6",
      "templateCode": "0x06000000000000D4",
      "templateExtend": "{\"materialMin\":\"\",\"materialMax\":\"\",\"textBindFont\":{}}",
      "templateRule": "{\"type\":\"normal\",\"rule\":{\"changeConfs\":[]},\"remark\":\"\",\"width\":720,\"height\":1280}",
      "title": "Explosion",
      "titleFromTemplate": "EX-3",
      "version": 131082,
      "virFlag": 0,
      "width": 0
    },
    {
      "appmaxcodeFromTemplate": "",
      "appmincodeFromTemplate": "",
      "countryCode": "OTHER",
      "downUrl": "https://rc.veresource.com/vcm/20200515/16121919/0x06000000000001DE.zip",
      "event": "",
      "eventFromTemplateInfo": "{\"code\":\"0\",\"parameter\":{}}",
      "extend": "{\"orderNoNewUser\":206}",
      "flagForGroup": 0,
      "groupCode": "201911291433262561",
      "height": 720,
      "hotFlag": 0,
      "iconFromTemplate": "https://d2hyio9ps90xn9.cloudfront.net/videodata/fx/explosion/4.webp",
      "id": 642156,
      "intro": "Explosion",
      "introFromTemplate": "",
      "lang": "en_OTHER",
      "model": "videoshow_effect",
      "newFlag": 0,
      "orderNoFromInfo": 3,
      "orderNoFromTemplate": 3,
      "previewtype": 2,
      "previewurl": "",
      "productId": 2,
      "recommendFlag": 0,
      "showEditFlag": 1,
      "showEditFlagGroup": 1,
      "showImg": "",
      "subTcid": "0",
      "tcid": "6",
      "templateCode": "0x06000000000001DE",
      "templateExtend": "{\"dataType\":\"0\",\"singleVideoDuration\":1000,\"materialMin\":\"\",\"materialMax\":\"\",\"textBindFont\":{}}",
      "templateRule": "{\"type\":\"normal\",\"rule\":{\"changeConfs\":[]},\"remark\":\"\",\"width\":1280,\"height\":720,\"pretreatment_type\":\"\"}",
      "title": "Explosion",
      "titleFromTemplate": "EX-4",
      "version": 196620,
      "virFlag": 0,
      "width": 1280
    },
    {
      "appmaxcodeFromTemplate": "",
      "appmincodeFromTemplate": "",
      "countryCode": "OTHER",
      "downUrl": "https://rc.veresource.com/vcm/20191022/14012828/0x0600000000000090.zip",
      "event": "",
      "eventFromTemplateInfo": "{\"code\":\"0\",\"parameter\":{}}",
      "extend": "{\"orderNoNewUser\":206}",
      "flagForGroup": 0,
      "groupCode": "201911291433262561",
      "height": 0,
      "hotFlag": 0,
      "iconFromTemplate": "https://d2hyio9ps90xn9.cloudfront.net/videodata/fx/explosion/5.webp",
      "id": 420475,
      "intro": "Explosion",
      "introFromTemplate": "",
      "lang": "en_OTHER",
      "model": "videoshow_effect",
      "newFlag": 0,
      "orderNoFromInfo": 4,
      "orderNoFromTemplate": 4,
      "previewtype": 3,
      "previewurl": "https://rs.videoshow.mobi/v2/images/vmake/fx/explosion/5.gif",
      "productId": 2,
      "recommendFlag": 0,
      "showEditFlag": 1,
      "showEditFlagGroup": 1,
      "showImg": "",
      "subTcid": "0",
      "tcid": "6",
      "templateCode": "0x0600000000000090",
      "templateExtend": "{\"materialMin\":\"\",\"materialMax\":\"\",\"textBindFont\":{}}",
      "title": "Explosion",
      "titleFromTemplate": "EX-5",
      "version": 131082,
      "virFlag": 0,
      "width": 0
    },
    {
      "appmaxcodeFromTemplate": "",
      "appmincodeFromTemplate": "",
      "countryCode": "OTHER",
      "downUrl": "https://rc.veresource.com/vcm/20200615/171253/0x0600000000000216.zip",
      "event": "",
      "eventFromTemplateInfo": "{\"code\":\"0\",\"parameter\":{}}",
      "extend": "{\"orderNoNewUser\":206}",
      "flagForGroup": 0,
      "groupCode": "201911291433262561",
      "height": 1280,
      "hotFlag": 0,
      "iconFromTemplate": "https://d2hyio9ps90xn9.cloudfront.net/videodata/fx/explosion/6.webp",
      "id": 730143,
      "intro": "Explosion",
      "lang": "en_OTHER",
      "model": "videoshow_effect",
      "newFlag": 0,
      "orderNoFromInfo": 5,
      "orderNoFromTemplate": 5,
      "previewtype": 2,
      "productId": 2,
      "recommendFlag": 0,
      "showEditFlag": 1,
      "showEditFlagGroup": 1,
      "subTcid": "0",
      "tcid": "6",
      "templateCode": "0x0600000000000216",
      "templateExtend": "{\"dataType\":\"0\",\"singleVideoDuration\":1000,\"materialMin\":\"\",\"materialMax\":\"\",\"textBindFont\":{}}",
      "templateRule": "{\"type\":\"normal\",\"rule\":{\"changeConfs\":[],\"attrCartoonArgs\":{\"enableAttribute\":false,\"manEuroTheme\":\"\",\"womanEuroTheme\":\"\",\"manAfricaTheme\":\"\",\"womanAfricaTheme\":\"\",\"manAsiaTheme\":\"\",\"womanAsiaTheme\":\"\",\"manIndiaTheme\":\"\",\"womanIndiaTheme\":\"\",\"manOthersTheme\":\"\",\"womanOthersTheme\":\"\"}},\"remark\":\"\",\"width\":720,\"height\":1280,\"pretreatment_type\":\"\"}",
      "title": "Explosion",
      "titleFromTemplate": "EX-6",
      "version": 196620,
      "virFlag": 0,
      "width": 720
    },
    {
      "appmaxcodeFromTemplate": "",
      "appmincodeFromTemplate": "",
      "countryCode": "OTHER",
      "downUrl": "https://rc.veresource.com/vcm/20191022/17235858/0x060000000000008D.zip",
      "event": "",
      "eventFromTemplateInfo": "{\"code\":\"0\",\"parameter\":{}}",
      "extend": "{\"orderNoNewUser\":206}",
      "flagForGroup": 0,
      "groupCode": "201911291433262561",
      "height": 0,
      "hotFlag": 0,
      "iconFromTemplate": "https://d2hyio9ps90xn9.cloudfront.net/videodata/fx/explosion/7.webp",
      "id": 420472,
      "intro": "Explosion",
      "introFromTemplate": "",
      "lang": "en_OTHER",
      "model": "videoshow_effect",
      "newFlag": 0,
      "orderNoFromInfo": 6,
      "orderNoFromTemplate": 6,
      "previewtype": 3,
      "previewurl": "https://rs.videoshow.mobi/v2/images/vmake/fx/explosion/7.gif",
      "productId": 2,
      "recommendFlag": 0,
      "showEditFlag": 1,
      "showEditFlagGroup": 1,
      "showImg": "",
      "subTcid": "0",
      "tcid": "6",
      "templateCode": "0x060000000000008D",
      "templateExtend": "{\"materialMin\":\"\",\"materialMax\":\"\",\"textBindFont\":{}}",
      "title": "Explosion",
      "titleFromTemplate": "EX-7",
      "version": 131082,
      "virFlag": 0,
      "width": 0
    },
    {
      "appmaxcodeFromTemplate": "",
      "appmincodeFromTemplate": "",
      "countryCode": "OTHER",
      "downUrl": "https://rc.veresource.com/vcm/20200615/171148/0x0600000000000217.zip",
      "event": "",
      "eventFromTemplateInfo": "{\"code\":\"0\",\"parameter\":{}}",
      "extend": "{\"orderNoNewUser\":206}",
      "flagForGroup": 0,
      "groupCode": "201911291433262561",
      "height": 1280,
      "hotFlag": 0,
      "iconFromTemplate": "https://d2hyio9ps90xn9.cloudfront.net/videodata/fx/explosion/8.webp",
      "id": 730142,
      "intro": "Explosion",
      "lang": "en_OTHER",
      "model": "videoshow_effect",
      "newFlag": 0,
      "orderNoFromInfo": 7,
      "orderNoFromTemplate": 7,
      "previewtype": 2,
      "productId": 2,
      "recommendFlag": 0,
      "showEditFlag": 1,
      "showEditFlagGroup": 1,
      "subTcid": "0",
      "tcid": "6",
      "templateCode": "0x0600000000000217",
      "templateExtend": "{\"dataType\":\"0\",\"singleVideoDuration\":1000,\"materialMin\":\"\",\"materialMax\":\"\",\"textBindFont\":{}}",
      "templateRule": "{\"type\":\"normal\",\"rule\":{\"changeConfs\":[],\"attrCartoonArgs\":{\"enableAttribute\":false,\"manEuroTheme\":\"\",\"womanEuroTheme\":\"\",\"manAfricaTheme\":\"\",\"womanAfricaTheme\":\"\",\"manAsiaTheme\":\"\",\"womanAsiaTheme\":\"\",\"manIndiaTheme\":\"\",\"womanIndiaTheme\":\"\",\"manOthersTheme\":\"\",\"womanOthersTheme\":\"\"}},\"remark\":\"\",\"width\":720,\"height\":1280,\"pretreatment_type\":\"\"}",
      "title": "Explosion",
      "titleFromTemplate": "EX-8",
      "version": 196620,
      "virFlag": 0,
      "width": 720
    },
    {
      "appmaxcodeFromTemplate": "",
      "appmincodeFromTemplate": "",
      "countryCode": "OTHER",
      "downUrl": "https://rc.veresource.com/vcm/20191022/14010909/0x06000000000000D3.zip",
      "event": "",
      "eventFromTemplateInfo": "{\"code\":\"0\",\"parameter\":{}}",
      "extend": "{\"orderNoNewUser\":206}",
      "flagForGroup": 0,
      "groupCode": "201911291433262561",
      "height": 0,
      "hotFlag": 0,
      "iconFromTemplate": "https://d2hyio9ps90xn9.cloudfront.net/videodata/fx/explosion/9.webp",
      "id": 420481,
      "intro": "Explosion",
      "introFromTemplate": "",
      "lang": "en_OTHER",
      "model": "videoshow_effect",
      "newFlag": 0,
      "orderNoFromInfo": 8,
      "orderNoFromTemplate": 8,
      "previewtype": 3,
      "previewurl": "https://rs.videoshow.mobi/v2/images/vmake/fx/explosion/9.gif",
      "productId": 2,
      "recommendFlag": 0,
      "showEditFlag": 1,
      "showEditFlagGroup": 1,
      "showImg": "",
      "subTcid": "0",
      "tcid": "6",
      "templateCode": "0x06000000000000D3",
      "templateExtend": "{\"materialMin\":\"\",\"materialMax\":\"\",\"textBindFont\":{}}",
      "title": "Explosion",
      "titleFromTemplate": "EX-9",
      "version": 131082,
      "virFlag": 0,
      "width": 0
    },
    {
      "appmaxcodeFromTemplate": "",
      "appmincodeFromTemplate": "",
      "countryCode": "OTHER",
      "downUrl": "https://rc.veresource.com/vcm/20191022/16054545/0x06000000000000B1.zip",
      "event": "",
      "eventFromTemplateInfo": "{\"code\":\"0\",\"parameter\":{}}",
      "extend": "{\"orderNoNewUser\":206}",
      "flagForGroup": 0,
      "groupCode": "201911291433262561",
      "height": 0,
      "hotFlag": 0,
      "iconFromTemplate": "https://d2hyio9ps90xn9.cloudfront.net/videodata/fx/explosion/10.webp",
      "id": 420479,
      "intro": "Explosion",
      "introFromTemplate": "",
      "lang": "en_OTHER",
      "model": "videoshow_effect",
      "newFlag": 0,
      "orderNoFromInfo": 9,
      "orderNoFromTemplate": 9,
      "previewtype": 3,
      "previewurl": "https://rs.videoshow.mobi/v2/images/vmake/fx/explosion/10.gif",
      "productId": 2,
      "recommendFlag": 0,
      "showEditFlag": 1,
      "showEditFlagGroup": 1,
      "showImg": "",
      "subTcid": "0",
      "tcid": "6",
      "templateCode": "0x06000000000000B1",
      "templateExtend": "{\"materialMin\":\"\",\"materialMax\":\"\",\"textBindFont\":{}}",
      "title": "Explosion",
      "titleFromTemplate": "EX-10",
      "version": 131082,
      "virFlag": 0,
      "width": 0
    },
    {
      "appmaxcodeFromTemplate": "",
      "appmincodeFromTemplate": "",
      "countryCode": "OTHER",
      "downUrl": "https://rc.veresource.com/vcm/20191022/16050505/0x06000000000000B4.zip",
      "event": "",
      "eventFromTemplateInfo": "{\"code\":\"0\",\"parameter\":{}}",
      "extend": "{\"orderNoNewUser\":206}",
      "flagForGroup": 0,
      "groupCode": "201911291433262561",
      "height": 0,
      "hotFlag": 0,
      "iconFromTemplate": "https://d2hyio9ps90xn9.cloudfront.net/videodata/fx/explosion/11.webp",
      "id": 1007670,
      "intro": "Explosion",
      "introFromTemplate": "",
      "lang": "en_OTHER",
      "model": "videoshow_effect",
      "newFlag": 0,
      "orderNoFromInfo": 10,
      "orderNoFromTemplate": 10,
      "previewtype": 3,
      "previewurl": "https://rs.videoshow.mobi/v2/images/vmake/fx/explosion/11.gif",
      "productId": 2,
      "recommendFlag": 0,
      "showEditFlag": 1,
      "showEditFlagGroup": 1,
      "showImg": "",
      "subTcid": "0",
      "tcid": "6",
      "templateCode": "0x06000000000000B4",
      "templateExtend": "{\"materialMin\":\"\",\"materialMax\":\"\",\"textBindFont\":{}}",
      "title": "Explosion",
      "titleFromTemplate": "EX-11",
      "version": 131082,
      "virFlag": 0,
      "width": 0
    },
    {
      "appmaxcodeFromTemplate": "",
      "appmincodeFromTemplate": "",
      "countryCode": "OTHER",
      "downUrl": "https://rc.veresource.com/vcm/20200515/17420909/0x06000000000001E0.zip",
      "event": "",
      "eventFromTemplateInfo": "{\"code\":\"0\",\"parameter\":{}}",
      "extend": "{\"orderNoNewUser\":206}",
      "flagForGroup": 0,
      "groupCode": "201911291433262561",
      "height": 1280,
      "hotFlag": 0,
      "iconFromTemplate": "https://d2hyio9ps90xn9.cloudfront.net/videodata/fx/explosion/12.webp",
      "id": 642160,
      "intro": "Explosion",
      "introFromTemplate": "",
      "lang": "en_OTHER",
      "model": "videoshow_effect",
      "newFlag": 0,
      "orderNoFromInfo": 11,
      "orderNoFromTemplate": 11,
      "previewtype": 2,
      "previewurl": "",
      "productId": 2,
      "recommendFlag": 0,
      "showEditFlag": 1,
      "showEditFlagGroup": 1,
      "showImg": "",
      "subTcid": "0",
      "tcid": "6",
      "templateCode": "0x06000000000001E0",
      "templateExtend": "{\"dataType\":\"0\",\"singleVideoDuration\":1000,\"materialMin\":\"\",\"materialMax\":\"\",\"textBindFont\":{}}",
      "templateRule": "{\"type\":\"normal\",\"rule\":{\"changeConfs\":[]},\"remark\":\"\",\"width\":720,\"height\":1280,\"pretreatment_type\":\"\"}",
      "title": "Explosion",
      "titleFromTemplate": "EX-12",
      "version": 196620,
      "virFlag": 0,
      "width": 720
    },
    {
      "appmaxcodeFromTemplate": "",
      "appmincodeFromTemplate": "",
      "countryCode": "OTHER",
      "downUrl": "https://rc.veresource.com/vcm/20191022/16044848/0x06000000000000B5.zip",
      "event": "",
      "eventFromTemplateInfo": "{\"code\":\"0\",\"parameter\":{}}",
      "extend": "{\"orderNoNewUser\":206}",
      "flagForGroup": 0,
      "groupCode": "201911291433262561",
      "height": 0,
      "hotFlag": 0,
      "iconFromTemplate": "https://d2hyio9ps90xn9.cloudfront.net/videodata/fx/explosion/13.webp",
      "id": 420482,
      "intro": "Explosion",
      "introFromTemplate": "",
      "lang": "en_OTHER",
      "model": "videoshow_effect",
      "newFlag": 0,
      "orderNoFromInfo": 12,
      "orderNoFromTemplate": 12,
      "previewtype": 3,
      "previewurl": "https://rs.videoshow.mobi/v2/images/vmake/fx/explosion/13.gif",
      "productId": 2,
      "recommendFlag": 0,
      "showEditFlag": 1,
      "showEditFlagGroup": 1,
      "showImg": "",
      "subTcid": "0",
      "tcid": "6",
      "templateCode": "0x06000000000000B5",
      "templateExtend": "{\"materialMin\":\"\",\"materialMax\":\"\",\"textBindFont\":{}}",
      "title": "Explosion",
      "titleFromTemplate": "EX-13",
      "version": 131082,
      "virFlag": 0,
      "width": 0
    },
    {
      "appmaxcodeFromTemplate": "",
      "appmincodeFromTemplate": "",
      "countryCode": "OTHER",
      "downUrl": "http://rc.veresource.com/template/videoshowvideo/20170324/16544141/0x0600000000000096.zip",
      "event": "",
      "eventFromTemplateInfo": "{\"code\":\"0\",\"parameter\":{}}",
      "extend": "{\"orderNoNewUser\":206}",
      "flagForGroup": 0,
      "groupCode": "201911291433262561",
      "height": 0,
      "hotFlag": 0,
      "iconFromTemplate": "https://d2hyio9ps90xn9.cloudfront.net/videodata/fx/explosion/14.webp",
      "id": 420478,
      "intro": "Explosion",
      "introFromTemplate": "",
      "lang": "en_OTHER",
      "model": "videoshow_effect",
      "newFlag": 0,
      "orderNoFromInfo": 13,
      "orderNoFromTemplate": 13,
      "previewtype": 3,
      "previewurl": "https://rs.videoshow.mobi/v2/images/vmake/fx/explosion/14.gif",
      "productId": 2,
      "recommendFlag": 0,
      "showEditFlag": 1,
      "showEditFlagGroup": 1,
      "showImg": "",
      "subTcid": "0",
      "tcid": "6",
      "templateCode": "0x0600000000000096",
      "templateExtend": "{\"materialMin\":\"\",\"materialMax\":\"\",\"textBindFont\":{}}",
      "templateRule": "{\"type\":\"normal\",\"rule\":{\"changeConfs\":[]},\"remark\":\"\",\"width\":720,\"height\":1280}",
      "title": "Explosion",
      "titleFromTemplate": "EX-14",
      "version": 131082,
      "virFlag": 0,
      "width": 0
    },
    {
      "appmaxcodeFromTemplate": "",
      "appmincodeFromTemplate": "",
      "countryCode": "OTHER",
      "downUrl": "https://rc.veresource.com/vcm/20200713/155140/0x0600000000000237.zip",
      "event": "",
      "eventFromTemplateInfo": "{\"code\":\"0\",\"parameter\":{}}",
      "extend": "{\"orderNoNewUser\":206}",
      "flagForGroup": 0,
      "groupCode": "201911291433262561",
      "height": 720,
      "hotFlag": 0,
      "iconFromTemplate": "https://d2hyio9ps90xn9.cloudfront.net/videodata/fx/explosion/15.webp",
      "id": 855639,
      "intro": "Explosion",
      "lang": "en_OTHER",
      "model": "videoshow_effect",
      "newFlag": 0,
      "orderNoFromInfo": 14,
      "orderNoFromTemplate": 14,
      "previewtype": 2,
      "productId": 2,
      "recommendFlag": 0,
      "showEditFlag": 1,
      "showEditFlagGroup": 1,
      "subTcid": "0",
      "tcid": "6",
      "templateCode": "0x0600000000000237",
      "templateExtend": "{\"dataType\":\"0\",\"singleVideoDuration\":1000,\"textBindFont\":{}}",
      "templateRule": "{\"type\":\"normal\",\"rule\":{\"changeConfs\":[]},\"remark\":\"\",\"width\":1280,\"height\":720,\"pretreatment_type\":\"\"}",
      "title": "Explosion",
      "titleFromTemplate": "EX-15",
      "version": 196620,
      "virFlag": 0,
      "width": 1280
    },
    {
      "appmaxcodeFromTemplate": "",
      "appmincodeFromTemplate": "",
      "countryCode": "OTHER",
      "downUrl": "https://rc.veresource.com/vcm/20191022/17234343/0x060000000000008E.zip",
      "event": "",
      "eventFromTemplateInfo": "{\"code\":\"0\",\"parameter\":{}}",
      "extend": "{\"orderNoNewUser\":206}",
      "flagForGroup": 0,
      "groupCode": "201911291433262561",
      "height": 0,
      "hotFlag": 0,
      "iconFromTemplate": "https://d2hyio9ps90xn9.cloudfront.net/videodata/fx/explosion/16.webp",
      "id": 420473,
      "intro": "Explosion",
      "introFromTemplate": "",
      "lang": "en_OTHER",
      "model": "videoshow_effect",
      "newFlag": 0,
      "orderNoFromInfo": 15,
      "orderNoFromTemplate": 15,
      "previewtype": 3,
      "previewurl": "https://rs.videoshow.mobi/v2/images/vmake/fx/explosion/16.gif",
      "productId": 2,
      "recommendFlag": 0,
      "showEditFlag": 1,
      "showEditFlagGroup": 1,
      "showImg": "",
      "subTcid": "0",
      "tcid": "6",
      "templateCode": "0x060000000000008E",
      "templateExtend": "{\"materialMin\":\"\",\"materialMax\":\"\",\"textBindFont\":{}}",
      "title": "Explosion",
      "titleFromTemplate": "EX-16",
      "version": 131082,
      "virFlag": 0,
      "width": 0
    }
  ],
  "message": "successful",
  "success": true
}