{
  "makeUpInfos": [
    {
      "orderId": 11,
      "description": "",
      "name": "Free_2",
      "classifyId": 4,
      "assetsInfos": [
        {
          "subStatus": 0,
          "assetsUrl": "https://d2hyio9ps90xn9.cloudfront.net/snapix/data/makeup/katie.zip",
          "color": "0",
          "makeupId": 18,
          "makeupName": "Katie",
          "orderId": 0,
          "endTime": 1827628801,
          "previewPhoto": "file:///android_asset/makeup/photos/24.jpg",
          "makeupType": "default",
          "iconUrl": ""
        },
        {
          "subStatus": 0,
          "assetsUrl": "https://d2hyio9ps90xn9.cloudfront.net/snapix/data/makeup/caroline.zip",
          "color": "0",
          "makeupId": 19,
          "makeupName": "Caroline",
          "orderId": 1,
          "endTime": 1827628991,
          "previewPhoto": "file:///android_asset/makeup/photos/25.jpg",
          "makeupType": "default",
          "iconUrl": ""
        },
        {
          "subStatus": 0,
          "assetsUrl": "https://d2hyio9ps90xn9.cloudfront.net/snapix/data/makeup/tiffany.zip",
          "color": "0",
          "makeupId": 20,
          "makeupName": "Tiffany",
          "orderId": 2,
          "endTime": 1827629112,
          "previewPhoto": "file:///android_asset/makeup/photos/26.jpg",
          "makeupType": "default",
          "iconUrl": ""
        },
        {
          "subStatus": 0,
          "assetsUrl": "https://d2hyio9ps90xn9.cloudfront.net/snapix/data/makeup/kylie.zip",
          "color": "0",
          "makeupId": 21,
          "makeupName": "Kylie",
          "orderId": 3,
          "endTime": 1827629291,
          "previewPhoto": "file:///android_asset/makeup/photos/27.jpg",
          "makeupType": "default",
          "iconUrl": ""
        },
        {
          "subStatus": 0,
          "assetsUrl": "https://d2hyio9ps90xn9.cloudfront.net/snapix/data/makeup/alice.zip",
          "color": "0",
          "makeupId": 22,
          "makeupName": "Alice",
          "orderId": 4,
          "endTime": 1827629441,
          "previewPhoto": "file:///android_asset/makeup/photos/28.jpg",
          "makeupType": "default",
          "iconUrl": ""
        },
        {
          "subStatus": 0,
          "assetsUrl": "https://d2hyio9ps90xn9.cloudfront.net/snapix/data/makeup/lisa.zip",
          "color": "0",
          "makeupId": 23,
          "makeupName": "Lisa",
          "orderId": 5,
          "endTime": 1827629472,
          "previewPhoto": "file:///android_asset/makeup/photos/29.jpg",
          "makeupType": "default",
          "iconUrl": ""
        },
        {
          "subStatus": 0,
          "assetsUrl": "https://d2hyio9ps90xn9.cloudfront.net/snapix/data/makeup/hailey.zip",
          "color": "0",
          "makeupId": 24,
          "makeupName": "Hailey",
          "orderId": 6,
          "endTime": 1827629541,
          "previewPhoto": "file:///android_asset/makeup/photos/30.jpg",
          "makeupType": "default",
          "iconUrl": ""
        },
        {
          "subStatus": 0,
          "assetsUrl": "https://d2hyio9ps90xn9.cloudfront.net/snapix/data/makeup/jennie.zip",
          "color": "0",
          "makeupId": 25,
          "makeupName": "Jennie",
          "orderId": 7,
          "endTime": 1827629585,
          "previewPhoto": "file:///android_asset/makeup/photos/31.jpg",
          "makeupType": "default",
          "iconUrl": ""
        },
        {
          "subStatus": 0,
          "assetsUrl": "https://d2hyio9ps90xn9.cloudfront.net/snapix/data/makeup/selena.zip",
          "color": "0",
          "makeupId": 26,
          "makeupName": "Selena",
          "orderId": 8,
          "endTime": 1827629695,
          "previewPhoto": "file:///android_asset/makeup/photos/32.jpg",
          "makeupType": "default",
          "iconUrl": ""
        },
        {
          "subStatus": 0,
          "assetsUrl": "https://d2hyio9ps90xn9.cloudfront.net/snapix/data/makeup/ruby.zip",
          "color": "0",
          "makeupId": 27,
          "makeupName": "Ruby",
          "orderId": 9,
          "endTime": 1827629725,
          "previewPhoto": "file:///android_asset/makeup/photos/33.jpg",
          "makeupType": "default",
          "iconUrl": ""
        }
      ]
    },
    {
      "orderId": 9,
      "description": "",
      "name": "VIP",
      "classifyId": 3,
      "assetsInfos": [
        {
          "subStatus": 1,
          "assetsUrl": "https://d2hyio9ps90xn9.cloudfront.net/snapix/data/makeup/olivia.zip",
          "color": "000000",
          "makeupId": 61,
          "makeupName": "Olivia",
          "orderId": -17,
          "endTime": 1830249000,
          "previewPhoto": "file:///android_asset/makeup/photos/1.jpg",
          "makeupType": "default",
          "iconUrl": ""
        },
        {
          "subStatus": 1,
          "assetsUrl": "https://d2hyio9ps90xn9.cloudfront.net/snapix/data/makeup/charlotte.zip",
          "color": "000000",
          "makeupId": 58,
          "makeupName": "Charlotte",
          "orderId": -14,
          "endTime": 1925004000,
          "previewPhoto": "file:///android_asset/makeup/photos/2.jpg",
          "makeupType": "default",
          "iconUrl": ""
        },
        {
          "subStatus": 0,
          "assetsUrl": "https://d2hyio9ps90xn9.cloudfront.net/snapix/data/makeup/amelia.zip",
          "color": "000000",
          "makeupId": 57,
          "makeupName": "Amelia",
          "orderId": -13,
          "endTime": 1893482820,
          "previewPhoto": "file:///android_asset/makeup/photos/3.jpg",
          "makeupType": "default",
          "iconUrl": ""
        },
        {
          "subStatus": 1,
          "assetsUrl": "https://d2hyio9ps90xn9.cloudfront.net/snapix/data/makeup/harper.zip",
          "color": "000000",
          "makeupId": 55,
          "makeupName": "Harper",
          "orderId": -12,
          "endTime": 1924945020,
          "previewPhoto": "file:///android_asset/makeup/photos/4.jpg",
          "makeupType": "default",
          "iconUrl": ""
        },
        {
          "subStatus": 0,
          "assetsUrl": "https://d2hyio9ps90xn9.cloudfront.net/snapix/data/makeup/camila.zip",
          "color": "000000",
          "makeupId": 56,
          "makeupName": "Camila",
          "orderId": -11,
          "endTime": 1893409140,
          "previewPhoto": "file:///android_asset/makeup/photos/5.jpg",
          "makeupType": "default",
          "iconUrl": ""
        },
        {
          "subStatus": 1,
          "assetsUrl": "https://d2hyio9ps90xn9.cloudfront.net/snapix/data/makeup/emily.zip",
          "color": "000000",
          "makeupId": 53,
          "makeupName": "Emily",
          "orderId": -10,
          "endTime": 1893402660,
          "previewPhoto": "file:///android_asset/makeup/photos/6.jpg",
          "makeupType": "default",
          "iconUrl": ""
        },
        {
          "subStatus": 1,
          "assetsUrl": "https://d2hyio9ps90xn9.cloudfront.net/snapix/data/makeup/ella.zip",
          "color": "000000",
          "makeupId": 54,
          "makeupName": "Ella",
          "orderId": -9,
          "endTime": 1893404580,
          "previewPhoto": "file:///android_asset/makeup/photos/7.jpg",
          "makeupType": "default",
          "iconUrl": ""
        },
        {
          "subStatus": 0,
          "assetsUrl": "https://d2hyio9ps90xn9.cloudfront.net/snapix/data/makeup/chloe.zip",
          "color": "000000",
          "makeupId": 52,
          "makeupName": "Chloe",
          "orderId": -8,
          "endTime": 1893479100,
          "previewPhoto": "file:///android_asset/makeup/photos/8.jpg",
          "makeupType": "default",
          "iconUrl": ""
        },
        {
          "subStatus": 1,
          "assetsUrl": "https://d2hyio9ps90xn9.cloudfront.net/snapix/data/makeup/grace.zip",
          "color": "000000",
          "makeupId": 50,
          "makeupName": "Grace",
          "orderId": -7,
          "endTime": 1893483900,
          "previewPhoto": "file:///android_asset/makeup/photos/9.jpg",
          "makeupType": "default",
          "iconUrl": ""
        },
        {
          "subStatus": 1,
          "assetsUrl": "https://d2hyio9ps90xn9.cloudfront.net/snapix/data/makeup/ellie.zip",
          "color": "000000",
          "makeupId": 51,
          "makeupName": "Ellie",
          "orderId": -6,
          "endTime": 1893484080,
          "previewPhoto": "file:///android_asset/makeup/photos/10.jpg",
          "makeupType": "default",
          "iconUrl": ""
        },
        {
          "subStatus": 1,
          "assetsUrl": "https://d2hyio9ps90xn9.cloudfront.net/snapix/data/makeup/nora.zip",
          "color": "0",
          "makeupId": 45,
          "makeupName": "Nora",
          "orderId": -5,
          "endTime": 1925006295,
          "previewPhoto": "file:///android_asset/makeup/photos/11.jpg",
          "makeupType": "default",
          "iconUrl": ""
        },
        {
          "subStatus": 1,
          "assetsUrl": "https://d2hyio9ps90xn9.cloudfront.net/snapix/data/makeup/victoria.zip",
          "color": "0",
          "makeupId": 42,
          "makeupName": "Victoria",
          "orderId": -4,
          "endTime": 1924965995,
          "previewPhoto": "file:///android_asset/makeup/photos/12.jpg",
          "makeupType": "default",
          "iconUrl": ""
        },
        {
          "subStatus": 1,
          "assetsUrl": "https://d2hyio9ps90xn9.cloudfront.net/snapix/data/makeup/hannah.zip",
          "color": "0",
          "makeupId": 43,
          "makeupName": "Hannah",
          "orderId": -3,
          "endTime": 1924966425,
          "previewPhoto": "file:///android_asset/makeup/photos/13.jpg",
          "makeupType": "default",
          "iconUrl": ""
        },
        {
          "subStatus": 1,
          "assetsUrl": "https://d2hyio9ps90xn9.cloudfront.net/snapix/data/makeup/lillian.zip",
          "color": "0",
          "makeupId": 34,
          "makeupName": "Lillian",
          "orderId": -2,
          "endTime": 1893415816,
          "previewPhoto": "file:///android_asset/makeup/photos/14.jpg",
          "makeupType": "default",
          "iconUrl": ""
        },
        {
          "subStatus": 1,
          "assetsUrl": "https://d2hyio9ps90xn9.cloudfront.net/snapix/data/makeup/lucy.zip",
          "color": "0",
          "makeupId": 35,
          "makeupName": "Lucy",
          "orderId": -2,
          "endTime": 1893415902,
          "previewPhoto": "file:///android_asset/makeup/photos/15.jpg",
          "makeupType": "default",
          "iconUrl": ""
        },
        {
          "subStatus": 1,
          "assetsUrl": "https://d2hyio9ps90xn9.cloudfront.net/snapix/data/makeup/naomi.zip",
          "color": "0",
          "makeupId": 40,
          "makeupName": "Naomi",
          "orderId": 0,
          "endTime": 1924945829,
          "previewPhoto": "file:///android_asset/makeup/photos/16.jpg",
          "makeupType": "default",
          "iconUrl": ""
        },
        {
          "subStatus": 1,
          "assetsUrl": "https://d2hyio9ps90xn9.cloudfront.net/snapix/data/makeup/claire.zip",
          "color": "0",
          "makeupId": 39,
          "makeupName": "Claire",
          "orderId": 0,
          "endTime": 1924945700,
          "previewPhoto": "file:///android_asset/makeup/photos/17.jpg",
          "makeupType": "default",
          "iconUrl": ""
        },
        {
          "subStatus": 1,
          "assetsUrl": "https://d2hyio9ps90xn9.cloudfront.net/snapix/data/makeup/ivy.zip",
          "color": "0",
          "makeupId": 38,
          "makeupName": "Ivy",
          "orderId": 0,
          "endTime": 1924945434,
          "previewPhoto": "file:///android_asset/makeup/photos/18.jpg",
          "makeupType": "default",
          "iconUrl": ""
        },
        {
          "subStatus": 1,
          "assetsUrl": "https://d2hyio9ps90xn9.cloudfront.net/snapix/data/makeup/mia.zip",
          "color": "0",
          "makeupId": 16,
          "makeupName": "Mia",
          "orderId": 47,
          "endTime": 1827642246,
          "previewPhoto": "file:///android_asset/makeup/photos/19.jpg",
          "makeupType": "default",
          "iconUrl": ""
        },
        {
          "subStatus": 1,
          "assetsUrl": "https://d2hyio9ps90xn9.cloudfront.net/snapix/data/makeup/bella.zip",
          "color": "0",
          "makeupId": 15,
          "makeupName": "Bella",
          "orderId": 48,
          "endTime": 1827639929,
          "previewPhoto": "file:///android_asset/makeup/photos/20.jpg",
          "makeupType": "default",
          "iconUrl": ""
        },
        {
          "subStatus": 1,
          "assetsUrl": "https://d2hyio9ps90xn9.cloudfront.net/snapix/data/makeup/christine.zip",
          "color": "0",
          "makeupId": 17,
          "makeupName": "Christine",
          "orderId": 49,
          "endTime": 1827642953,
          "previewPhoto": "file:///android_asset/makeup/photos/21.jpg",
          "makeupType": "default",
          "iconUrl": ""
        },
        {
          "subStatus": 1,
          "assetsUrl": "https://d2hyio9ps90xn9.cloudfront.net/snapix/data/makeup/jane.zip",
          "color": "0",
          "makeupId": 11,
          "makeupName": "Jane",
          "orderId": 51,
          "endTime": 1827655080,
          "previewPhoto": "file:///android_asset/makeup/photos/22.jpg",
          "makeupType": "default",
          "iconUrl": ""
        },
        {
          "subStatus": 1,
          "assetsUrl": "https://d2hyio9ps90xn9.cloudfront.net/snapix/data/makeup/audrey.zip",
          "color": "0",
          "makeupId": 12,
          "makeupName": "Audrey",
          "orderId": 52,
          "endTime": 1827655980,
          "previewPhoto": "file:///android_asset/makeup/photos/23.jpg",
          "makeupType": "default",
          "iconUrl": ""
        }
      ]
    }
  ],
  "length": 2,
  "ETag": "81c767d7216c3617f16029c06fa1659e"
}